{
  "type": "actor",
  "center-x": 15, "center-x": 220,
  "angle": 0,
  "primitives": [
    { "type": "symbol",
      "id": "head",
      "path": "phenomena-head.json",
      "x": 127, "y": 255,
      "center-x": 120, "center-y": 260,
      "visibility": true,
      "debug": true
    },
    { "type": "svg",
      "path": "phenomena-body.svg",
      "x": 15, "y": 220,
      "visibility": true,
      "debug": true
    },
    { "type": "symbol",
      "id": "arm-left",
      "path": "phenomena-arm-left.json",
      "x": 15, "y": 220,
      "visibility": true,
      "debug": true
    }
  ]
}
